beetsplug/cd/audio/audio_cd.py
beetsplug/cd/audio/audio_populate_mode.py
beetsplug/cd/audio/audio_track.py
beetsplug/cd/cd.py
beetsplug/cd/mp3/mp3_cd.py
beetsplug/cd/mp3/mp3_folder.py
beetsplug/cd/mp3/mp3_track.py
beetsplug/cd/track.py
beetsplug/cd_parser.py
beetsplug/cdman.py
beetsplug/config.py
beetsplug/dimensional_thread_pool_executor.py
beetsplug/m3uparser.py
beetsplug/printer.py
beetsplug/stats.py
beetsplug/util.py
beets_cdman-1.1.1.dist-info/LICENSE
beets_cdman-1.1.1.dist-info/METADATA
beets_cdman-1.1.1.dist-info/WHEEL
beets_cdman-1.1.1.dist-info/RECORD
