Metadata-Version: 2.3
Name: beets-cdman
Version: 1.1.1
Summary: Easily manage your CD collection with beets
License: GPL-3.0-only
Keywords: beets,cdman,cd,mp3,audio,cli,command-line,command,line,tool,yml,yaml
Author: Tactical Laptop Bag
Author-email: tacticallaptopbag@protonmail.com
Requires-Python: >=3.12,<4
Classifier: Development Status :: 5 - Production/Stable
Classifier: Intended Audience :: End Users/Desktop
Classifier: Environment :: Console
Classifier: Operating System :: OS Independent
Classifier: Topic :: Multimedia
Classifier: Topic :: Multimedia :: Sound/Audio
Classifier: Topic :: Multimedia :: Sound/Audio :: CD Audio
Classifier: Topic :: Multimedia :: Sound/Audio :: Conversion
Classifier: Programming Language :: Python
Classifier: Programming Language :: Python :: 3.12
Classifier: Programming Language :: Python :: 3.13
Classifier: Programming Language :: Python :: 3.14
Classifier: Programming Language :: Python :: 3.15
Classifier: License :: OSI Approved :: GNU General Public License v3 (GPLv3)
Requires-Dist: beets (>=2.3.1,<3.0.0)
Requires-Dist: confuse (>=2.0.1,<3.0.0)
Requires-Dist: ffmpeg-python (>=0.2.0,<0.3.0)
Requires-Dist: more-itertools (>=10.7.0,<11.0.0)
Requires-Dist: psutil (>=7.0.0,<8.0.0)
Requires-Dist: python-magic (>=0.4.27,<0.5.0)
Project-URL: Issues, https://github.com/TacticalLaptopBag/beets-cdman/issues
Project-URL: Repository, https://github.com/TacticalLaptopBag/beets-cdman
